pycertifier/__init__.py
pycertifier/api.py
pycertifier/autorenew.py
pycertifier/certifier.py
pycertifier/certifier_client.py
pycertifier/cli.py
pycertifier/constants.py
pycertifier/error.py
pycertifier/log.py
pycertifier/main.py
pycertifier/property.py
pycertifier/sectigo.py
pycertifier/xpki_client.py
pycertifier/resources/pycertifier-cert.crt
pycertifier/resources/pycertifier.cfg
pycertifier/resources/seed.p12
pycertifier/resources/seedtest.p12
pycertifier-1.0.5.dist-info/LICENSE
pycertifier-1.0.5.dist-info/METADATA
pycertifier-1.0.5.dist-info/WHEEL
pycertifier-1.0.5.dist-info/entry_points.txt
pycertifier-1.0.5.dist-info/top_level.txt
pycertifier-1.0.5.dist-info/RECORD
