Metadata-Version: 2.2
Name: pycertifier
Version: 1.0.5
Summary: CLI to request xPKI certificates
Author-email: Russell Benjamin <russell_benjamin@comcast.com>
License: Apache-2.0
Requires-Python: >=3.13
License-File: LICENSE
Requires-Dist: base58==2.1.1
Requires-Dist: certifi==2024.8.30
Requires-Dist: cffi==1.17.1
Requires-Dist: charset-normalizer==3.4.0
Requires-Dist: cryptography==43.0.1
Requires-Dist: idna==3.10
Requires-Dist: packaging==24.1
Requires-Dist: psutil==6.0.0
Requires-Dist: requests-pkcs12==1.25
Requires-Dist: requests-toolbelt==1.0.0
Requires-Dist: setuptools==75.2.0
Requires-Dist: urllib3==2.2.3
Requires-Dist: lockfile==0.12.2
Provides-Extra: dev
Requires-Dist: twine>=5.1.1; extra == "dev"
